fastai_category_encoders/__init__.py
fastai_category_encoders/base.py
fastai_category_encoders/export.py
fastai_category_encoders/ext_category_encoders.py
fastai_category_encoders/ext_fastai.py
fastai_category_encoders/ext_fasttext.py
fastai_category_encoders/functional.py
fastai_category_encoders/utils.py
fastai_category_encoders/ext_autoembedder/__init__.py
fastai_category_encoders/ext_autoembedder/autoembedder.py
fastai_category_encoders/ext_autoembedder/autoembedder_cat_encoder.py
fastai_category_encoders/ext_autoembedder/autoencoder.py
fastai_category_encoders/ext_autoembedder/loss.py
fastai_category_encoders/ext_autoembedder/tensor.py
fastai_category_encoders-0.0.4.dist-info/LICENSE
fastai_category_encoders-0.0.4.dist-info/METADATA
fastai_category_encoders-0.0.4.dist-info/WHEEL
fastai_category_encoders-0.0.4.dist-info/top_level.txt
fastai_category_encoders-0.0.4.dist-info/RECORD
