Metadata-Version: 2.1
Name: fastai-category-encoders
Version: 0.0.4
Summary: Category encoders integrated with Fast.ai 
Home-page: https://github.com/kireygroup/fastai-category-encoders
Author: Riccardo Sayn
Author-email: riccardo.sayn@kireygroup.com
License: MIT
Keywords: encoding,fastai,pytorch,python,pandas,data
Platform: UNKNOWN
Classifier: Development Status :: 3 - Alpha
Classifier: Intended Audience :: Developers
Classifier: Topic :: Scientific/Engineering :: Artificial Intelligence
Classifier: License :: OSI Approved :: MIT License
Classifier: Programming Language :: Python :: 3
Classifier: Programming Language :: Python :: 3.4
Classifier: Programming Language :: Python :: 3.5
Classifier: Programming Language :: Python :: 3.6
Classifier: Programming Language :: Python :: 3.7
Requires-Dist: fastai (>=2.1.5)
Requires-Dist: category-encoders
